{
  "success": true,
  "channel": "farsna",
  "channel_title": "خبرگزاری فارس",
  "channel_username": "@farsna",
  "channel_avatar": "bale:46627310:-5654198181771010303:1:65b5e3e3fd6f689ba762e8e859915b368211e6c76420e4b7",
  "channel_verified": true,
  "channel_subscribers": "1.79M",
  "channel_photos": null,
  "channel_videos": null,
  "channel_files": null,
  "channel_links": null,
  "channel_description": "حقیقت روشن می‌شود\n‌\n‌\nتبلیغات @Farsnews_ads\n\nارتباط  @FarsNews\n\nفارس‌پلاس @Fars_Plus\n‌\n ورزش @SportFars\n\n جهان @FarsNewsInt\n\nعکس @FarsImages \n\nپیام‌رسان‌ها @Farsna\n\nاینستاگرام instagram.com/fars_news\n\nتوییتر twitter.com/FarsNews_Agency",
  "total_posts": 51,
  "returned_posts": 51,
  "posts": [
    {
      "datetime": "2026-04-22T22:19:01+00:00",
      "time_text": "22:19",
      "link": "https://t.me/farsna/430856",
      "views": "219"
    },
    {
      "text": "‌\n🔴 سی‌ان‌ان: صنایع شیمیایی آلمان اعلام کرد که جنگ ایران «ضربهٔ شدیدی» به امیدها برای بهبود وضعیت اقتصادی آلمان وارد کرده و باید منتظر توقف تولید و تعدیل نیروها بود.\n@Farsna"
    },
    {
      "text": "‌ سونامی بحران انرژی اروپا به لوفت‌هانزا رسید  🔹شرکت هواپیمایی لوفت‌هانزای آلمان پس‌از دو برابر شدن قیمت سوخت جت به دلیل جنگ با ایران، ۲۰ هزار پرواز کوتاه‌مدت خود را لغو خواهد کرد.  🔹لوفت‌هانزا پیشتر اعلام کرده بود که به‌دلیل افزایش بی‌سابقۀ قیمت سوخت و ناپایداری…"
    },
    {
      "post_id": "430856"
    },
    {
      "datetime": "2026-04-22T22:09:01+00:00",
      "time_text": "22:09",
      "link": "https://t.me/farsna/430855",
      "views": "1.07K"
    },
    {
      "text": "🖼 روح‌الامین: یک پرچم آتش زدید، کل ایران شده پرچم\n\n🔹حسن روح‌الامین نقاش و هنرمند آئینی در شبکه‌ اجتماعی ایکس نوشت: «یه پرچم ایران آتش زدید، کل ایران شده پرچم. جمهوری اسلامی ایران حرم است.»\n\n@Farsna - Link"
    },
    {
      "photos": [
        "bale:46627310:4332306028614655746:1:65b5e3e3fd6f689ba7f102c586392a2d8211e6c76420e4b7"
      ]
    },
    {
      "post_id": "430855"
    },
    {
      "datetime": "2026-04-22T22:06:17+00:00",
      "time_text": "22:06",
      "link": "https://t.me/farsna/430854",
      "views": "1.36K"
    },
    {
      "text": "وزیر نیروی دریایی آمریکا هم استعفا داد\n\n🔹در ادامه روند کناره‌گیری اعضای دولت آمریکا، سخنگوی وزارت جنگ این کشور اعلام کرد «جان فیلان» وزیر نیروی دریایی نیز از سمت خود استعفا کرده است.\n@Farsna - Link"
    },
    {
      "photos": [
        "bale:46627310:-558125259306295549:1:65b5e3e3fd6f689b8d22b963116432278211e6c76420e4b7"
      ]
    },
    {
      "post_id": "430854"
    },
    {
      "datetime": "2026-04-22T22:04:30+00:00",
      "time_text": "22:04",
      "link": "https://t.me/farsna/430844",
      "views": "1.31K"
    },
    {
      "text": "📰 دکۀ روزنامه | پنج‌شنبه ۳ اردیبهشت ۱۴۰۵\n\n@Farsna"
    },
    {
      "photos": [
        "bale:46627310:-3353342071794491645:1:65b5e3e3fd6f689ba7f102c586392a2d8211e6c76420e4b7"
      ]
    },
    {
      "photos": [
        "bale:46627310:-4734197482739982592:1:65b5e3e3fd6f689b3174931620a3091a8211e6c76420e4b7"
      ]
    },
    {
      "photos": [
        "bale:46627310:8848339988513824514:1:65b5e3e3fd6f689ba7f102c586392a2d8211e6c76420e4b7"
      ]
    },
    {
      "photos": [
        "bale:46627310:3791522531861405443:1:65b5e3e3fd6f689b8d22b963116432278211e6c76420e4b7"
      ]
    },
    {
      "photos": [
        "bale:46627310:2834637991682318081:1:65b5e3e3fd6f689b8d22b963116432278211e6c76420e4b7"
      ]
    },
    {
      "photos": [
        "bale:46627310:5807001059642646273:1:65b5e3e3fd6f689b3174931620a3091a8211e6c76420e4b7"
      ]
    },
    {
      "photos": [
        "bale:46627310:-1686415508468850942:1:65b5e3e3fd6f689b8d22b963116432278211e6c76420e4b7"
      ]
    },
    {
      "photos": [
        "bale:46627310:6942741763036618499:1:65b5e3e3fd6f689ba7f102c586392a2d8211e6c76420e4b7"
      ]
    },
    {
      "photos": [
        "bale:46627310:-3002477099726790909:1:65b5e3e3fd6f689b8d22b963116432278211e6c76420e4b7"
      ]
    },
    {
      "photos": [
        "bale:46627310:-8376209969957232895:1:65b5e3e3fd6f689ba7f102c586392a2d8211e6c76420e4b7"
      ]
    },
    {
      "post_id": "430844"
    },
    {
      "datetime": "2026-04-22T22:00:02+00:00",
      "time_text": "22:00",
      "link": "https://t.me/farsna/430843",
      "views": "1.53K"
    },
    {
      "text": "🎥 سپاه را در یک جمله توصیف کنید\n\n🔹مردم قزوین در سالروز تأسیس سپاه پاسداران انقلاب اسلامی، تعریف خود از این نهاد را در قالب یک جمله بیان کردند.\n\n@Farsna"
    },
    {
      "post_id": "430843"
    },
    {
      "datetime": "2026-04-22T21:56:01+00:00",
      "time_text": "21:56",
      "link": "https://t.me/farsna/430842",
      "views": "1.88K"
    },
    {
      "text": "🔴 اتحادیهٔ اروپا: جنگ آمریکا با ایران، تاکنون ۲۸ میلیارد دلار هزینهٔ اضافی روی دست بخش انرژی اروپا گذاشته است.\n\n@Farsna"
    },
    {
      "post_id": "430842"
    },
    {
      "datetime": "2026-04-22T21:53:01+00:00",
      "time_text": "21:53",
      "link": "https://t.me/farsna/430841",
      "views": "2.2K"
    },
    {
      "text": "سی‌ان‌ان: ترامپ وضعیت حکومت ایران را «به‌شدت دچار گسست» توصیف کرده اما بسیاری از تحلیل‌گران معتقدند رهبری ایران منسجم‌تر از آن چیزی است که کاخ سفید می‌گوید\n\n🔹رهبری ایران کاملاً منسجم عمل کرده و ما این انسجام را در نحوهٔ پیشبرد جنگ و روند مذاکرات دیده‌ایم.\n@Farsna"
    },
    {
      "photos": [
        "bale:46627310:5743572907356790529:1:65b5e3e3fd6f689bcb7acf70ce22463c8211e6c76420e4b7"
      ]
    },
    {
      "post_id": "430841"
    },
    {
      "datetime": "2026-04-22T21:46:31+00:00",
      "time_text": "21:46",
      "link": "https://t.me/farsna/430840",
      "views": "2.15K"
    },
    {
      "text": "📹 #روایت | نکته جالبی که امام خامنه‌ای راجع به یک نوحه به حاج محمود کریمی گفتند&#33;\n\n@rahbari_plus"
    },
    {
      "videos": [
        "bale:46627310:7480518653791903489:1:65b5e3e3fd6f689b69c180d51cd25a6e78bd75520bbfc49a"
      ]
    },
    {
      "post_id": "430840"
    },
    {
      "datetime": "2026-04-22T21:44:31+00:00",
      "time_text": "21:44",
      "link": "https://t.me/farsna/430839",
      "views": "2.58K"
    },
    {
      "text": "‌ \nفقط ۲ بانک جریمه دیرکرد اقساط را برمی‌گردانند\n\n🔹گزارش‌های رسیده به فارس حاکی از آن است که بانک‌ها کماکان جریمه تاخیر در پرداخت اقساط را از مشتریان دریافت می‌کنند.\n \n🔹یک منبع در بانک مرکزی گفته به دلیل اینکه بانک‌ها دارای سهامدار هستند، بانک مرکزی هم نمی‌تواند آن‌ها را ملزم کند تا دریافت اقساط را عقب بیندازند یا جریمه نگیرند.\n\n🔹از میان تمام بانک‌های کشور تنها دو بانک ملت و ملی جریمه تاخیر در پرداخت اقساط را اخذ نخواهند کرد و جریمه‌های گرفته شده را پس می‌دهند.\n\n🔗شرح کامل این گزارش را از اینجا بخوانید.\n\n@Farsna"
    },
    {
      "text": "بخشودگی جریمه تأخیر اقساط وام‌های زیر ۷۰۰ میلیون تومان  🔹 بانک مرکزی: در صورت تأخیر مشتریان در پرداخت اقساط برای وام‌هایی که اصل تسهیلات آن‌ها کمتر از ۷۰۰ میلیون تومان است، جریمه‌ای بابت تأخیر اخذ نخواهد شد.  @Farsna - Link"
    },
    {
      "post_id": "430839"
    },
    {
      "datetime": "2026-04-22T21:33:29+00:00",
      "time_text": "21:33",
      "link": "https://t.me/farsna/430838",
      "views": "2.83K"
    },
    {
      "text": "🎥 شب پنجاه‌وسوم، همانند شب‌های اول در خرم‌آباد جای سوزن انداختن نیست\n\n@Farsna"
    },
    {
      "videos": [
        "bale:46627310:-5304782782459535613:1:65b5e3e3fd6f689bc906b7b453abe49b78bd75520bbfc49a"
      ]
    },
    {
      "post_id": "430838"
    },
    {
      "datetime": "2026-04-22T21:20:14+00:00",
      "time_text": "21:20",
      "link": "https://t.me/farsna/430837",
      "views": "3.13K"
    },
    {
      "text": "گزارش پنتاگون درباره تنگه هرمز که نمایندگان آمریکایی را «ناامید» کرد\n\n🔹در بحبوحه نگرانی آمریکایی‌ها از پیامد‌های اقتصادی جنگ ایران، واشنگتن‌پست روز چهارشنبه گزارش داد که طبق ارزیابی‌های پنتاگون، برگزاری هرگونه عملیات مین‌روبی در تنگه هرمز پیش از پایان جنگ عملاً قابل اجرا نیست و حتی پس از آن نیز ماه‌ها زمان می‌برد.\n\n🔹نظرسنجی‌های اخیر نشان داده‌اند که تصمیم رئیس‌جمهور آمریکا دونالد ترامپ برای آغاز جنگ با مخالفت اکثر آمریکایی‌ها همراه بوده و پایگاه سیاسی او را که تا حدی به دلیل وعده‌های مکررش برای اجتناب از درگیری‌های نظامی خارجی و تمرکز بر مسائل داخلی به او رأی داده بودند، دچار تفرقه کرده است.\n\n🔹از سوی دیگر، رسانه‌ها و سیاستمداران غربی به شدت درباره احتمال وجود مین در تنگه هرمز ابراز نگرانی کرده‌اند، در حالی که تاکنون گزارشی از سوی ایران درباره مین‌گذاری در این آبراهه منتشر نشده است.\n\n@FarsNewsInt - Link"
    },
    {
      "photos": [
        "bale:46627310:1824283048681873155:1:65b5e3e3fd6f689bc906b7b453abe49b8211e6c76420e4b7"
      ]
    },
    {
      "post_id": "430837"
    }
  ],
  "fetch_metadata": {
    "last_update": "2026-04-23T01:50:26.777655",
    "new_count": 5
  }
}