{
  "success": true,
  "channel": "matinsenpaii",
  "channel_title": "Matin SenPai",
  "channel_username": "@matinsenpaii",
  "channel_avatar": "bale:46627310:-6338603592322703613:1:65b5e3e3fd6f689b97ff6dc5759c5eb58211e6c76420e4b7",
  "channel_verified": false,
  "channel_subscribers": "58.5K",
  "channel_photos": null,
  "channel_videos": null,
  "channel_files": null,
  "channel_links": null,
  "channel_description": "یوتوبر انیمه و مانگا(الان کمی شبکه؟&#33;) - برنامه‌نویسِ ایده‌های باحال\n\n•YouTube:\nhttp://www.youtube.com/@Matin_SenPai\n\n•AniList:\nhttps://anilist.co/user/MatinSenPai\n\n•Github:\nhttps://github.com/MatinSenPai",
  "total_posts": 64,
  "returned_posts": 64,
  "posts": [
    {
      "datetime": "2026-04-21T21:40:22+00:00",
      "time_text": "21:40",
      "link": "https://t.me/MatinSenPaii/2800",
      "views": "6.44K"
    },
    {
      "text": "💬کمی مرتب کردن مطالب:\n\nخود متد:\nhttps://t.me/MatinSenPaii/2785\n\nمشکل پخش نشدن ویدئو:\n1- https://t.me/MatinSenPaii/2792\n2- https://t.me/MatinSenPaii/2793\n3- https://t.me/MatinSenPaii/2797\n4- https://t.me/WeebsDungeon/405897\n\nنکات مهم راجب این متد:\nhttps://t.me/MatinSenPaii/2799\n\nراجب آوردنش روی گوشی هم من موفق نشدم خودم. اما شما تست کنید ببینید چه میشه"
    },
    {
      "post_id": "2800"
    },
    {
      "datetime": "2026-04-21T20:48:35+00:00",
      "time_text": "20:48",
      "link": "https://t.me/MatinSenPaii/2799",
      "views": "12.5K"
    },
    {
      "text": "❓Aleskxyz:\n\n&rlm;توی استفاده از این روش چندتا نکته رو در نظر داشته باشید:\n- حتما از یه اکانت جداگانه استفاده کنید، احتمال اینکه اکانت شما به خاطر سواستفاده از این سرویس بسته بشه زیاده و اون وقت شما دسترسی به ایمیلهاتون رو هم از دست میدید.\n- تا حد امکان سعی کنید فقط برای استفاده کم حجم و ضروری ازش استفاده کنید. این سرویس برای حجم بالای درخواست طراحی نشده.\n- جاهایی که توی سیستم رفتید تغییر دادید تا گواهی خودتون رو نصب کنید رو به خاطر بسپارید تا بعد بتونید به حالت قبل برگردونید.\n\nفراگیر شدن این روش در حد ترافیک یه کشور قطعا با واکنش گوگل مواجه میشه و به زودی محدودش میکنن. فقط امیدوارم این محدودیت شامل خود این سرویس بشه و دامین فرانتینگ رو نبندن."
    },
    {
      "post_id": "2799"
    },
    {
      "datetime": "2026-04-21T18:37:11+00:00",
      "time_text": "18:37",
      "link": "https://t.me/MatinSenPaii/2798",
      "views": "20K"
    },
    {
      "text": "اگر این مشکل رو دارید\nبرید توی settings ویندوز\nقسمت Add or remove programs \nپایتون رو انتخاب کنید\nModify\nبعدش delete \nو مجددا که نصب میکنید، حتما تیک Add python to the .path رو بزنید همونطور که توی ویدئو گفتم"
    },
    {
      "text": "داش پایتونو پیدا نمیکنه میخوام پاک کنم پایتونو نصب کنم هم پاک نمیشه ارور میده چیکا کنم"
    },
    {
      "post_id": "2798"
    },
    {
      "datetime": "2026-04-21T18:30:48+00:00",
      "time_text": "18:30",
      "link": "https://t.me/MatinSenPaii/2797",
      "views": "20.8K"
    },
    {
      "text": "دوستانی که مشکل 502 و باز نشدن ویدیو های یوتیوب رو دارن\n\nبرن توی google script\nو کل متنو پاک کنن دوابره پیست کنن و روی deploy بزنن\nو مراحلو دوباره انجام بدن \nاون id که بهتون داد جدیده واردش کنید درست میشه"
    },
    {
      "post_id": "2797"
    },
    {
      "datetime": "2026-04-21T15:15:46+00:00",
      "time_text": "15:15",
      "link": "https://t.me/MatinSenPaii/2796",
      "views": "26.6K"
    },
    {
      "text": "برای رفتن بدون vpn توی سایت اسکریپت میتونید از این کانفیگ دوستمون استفاده کنید"
    },
    {
      "text": "{\n\"dns\": {\n\"hosts\": {"
    },
    {
      "post_id": "2796"
    },
    {
      "datetime": "2026-04-21T15:02:48+00:00",
      "time_text": "15:02",
      "link": "https://t.me/MatinSenPaii/2795",
      "views": "26.1K"
    },
    {
      "text": "قرار نبود لو بدین:))"
    },
    {
      "text": "پشماااااام   اینستا هم میاره 😂"
    },
    {
      "post_id": "2795"
    },
    {
      "datetime": "2026-04-21T15:02:36+00:00",
      "time_text": "15:02",
      "link": "https://t.me/MatinSenPaii/2794",
      "views": "26.2K"
    },
    {
      "text": "پشماااااام \n\nاینستا هم میاره 😂"
    },
    {
      "post_id": "2794"
    },
    {
      "datetime": "2026-04-21T15:02:35+00:00",
      "time_text": "15:02",
      "link": "https://t.me/MatinSenPaii/2793",
      "views": "25.7K"
    },
    {
      "text": "دوستان قضیه پخش نشدن ویدئو یعنی اینکه اصلا تونلتون درست وصل نشده .\nیعنی فرضا x.com هم نباید بالا بیاد . تلگرام هم نباید وصل شه"
    },
    {
      "post_id": "2793"
    },
    {
      "datetime": "2026-04-21T15:01:41+00:00",
      "time_text": "15:01",
      "link": "https://t.me/MatinSenPaii/2792",
      "views": "25.4K"
    },
    {
      "text": "واسه من باز نمیشد، وریفای tls رو خاموش کردم پلی شد"
    },
    {
      "post_id": "2792"
    },
    {
      "datetime": "2026-04-21T14:53:16+00:00",
      "time_text": "14:53",
      "link": "https://t.me/MatinSenPaii/2791",
      "views": "25.5K"
    },
    {
      "text": "این قضیه‌ی پخش نشدن ویدئوها ممکنه به اینترنتتون مربوط باشه چون توی ویدئو همونطور که دیدید، برای من پلی میشد. \n1- با اپراتور دیگه تست کنید. و مو به مو جلو برید طبق ویدئو.\n2- اگر نشد، لینک رو بفرستید به @TheGdriveXBot که واستون آپلود کنه توی درایو(فیلتر نیست) و ترجیحا از یه ایمیل غیرکاری و غیرمهم استفاده کنید\n\nپ.ن: من خودم با ایرانسل رفتم"
    },
    {
      "post_id": "2791"
    },
    {
      "datetime": "2026-04-21T13:56:29+00:00",
      "time_text": "13:56",
      "link": "https://t.me/MatinSenPaii/2790"
    },
    {
      "text": "Matin SenPai pinned a video"
    },
    {
      "post_id": "2790"
    },
    {
      "datetime": "2026-04-21T13:56:08+00:00",
      "time_text": "13:56",
      "link": "https://t.me/MatinSenPaii/2789",
      "views": "26.2K"
    },
    {
      "text": "ویدئو حجمش 200 مگابایت بود اونی که روی یوتوب آپلود کردم. باز فشرده کردم و واستون گذاشتم و صرفا دارم اینو میگم که بدونید به فکرتون هستم❤️ ممنونم از همه‌ی عزیزانی که VPN رسوندن به دست من تا این آموزش رو بتونم واستون درست کنم"
    },
    {
      "post_id": "2789"
    },
    {
      "datetime": "2026-04-21T13:54:11+00:00",
      "time_text": "13:54",
      "link": "https://t.me/MatinSenPaii/2788",
      "views": "26.2K"
    },
    {
      "text": "سهام Dastyar بعد از ویدئوی من: 📉\n(حرکت رونالدو روی نوشابه رو زدم)"
    },
    {
      "post_id": "2788"
    },
    {
      "datetime": "2026-04-21T13:53:25+00:00",
      "time_text": "13:53",
      "link": "https://t.me/MatinSenPaii/2787",
      "views": "32K"
    },
    {
      "text": "🔗لینک‌های داخلی ویدئو و فایل\nمدت زمان انقضا: 1 روز(سایت اجازه بیشترش رو نمیداد. کالبد باز آپ شد اونجا هم آپلود میکنم واستون)\n\nلینک داخلی ویدئو: https://guardnet.ir/f/matinsenpai-masterhttpvid\n\nلینک داخلی فایل: https://guardnet.ir/f/matinsenpai-masterhttpfile"
    },
    {
      "post_id": "2787"
    },
    {
      "datetime": "2026-04-21T13:47:35+00:00",
      "time_text": "13:47",
      "link": "https://t.me/MatinSenPaii/2786",
      "views": "30.4K"
    },
    {
      "text": "فایل مربوط به ویدئوی بالا. به زودی لینک‌های داخلی دانلود زیر همین پست قرار میگیره"
    },
    {
      "post_id": "2786"
    },
    {
      "datetime": "2026-04-21T13:47:26+00:00",
      "time_text": "13:47",
      "link": "https://t.me/MatinSenPaii/2785",
      "views": "43.8K"
    },
    {
      "text": "☠️بدون فیلترشکن به یوتوب وصل شو&#33; آموزش استفاده از Master Http Relay برای دور زدن فیلترینگ Youtube\n\n\nفایل استفاده شده توی ویدئو: https://t.me/MatinSenPaii/2786\nدستور اجرا: python main.py\nآموزش متنی: https://github.com/masterking32/MasterHttpRelayVPN/blob/python_testing/README_FA.md\n\n\nتوی این ویدئو بهتون یاد میدم که چطوری به راحتی با اسکریپت MasterHttpRelay بتونید فیلترینگ یوتوب رو دور بزنید توی شرایط حال حاضر اینترنت&#33;\n\n⭐️  کاملاً رایگان\n⭐️  سرعت بسیار بالا\n⭐️  بدون نیاز به دانش شبکه\n\n⚠️ پیش‌نیازها و نکات مهم: \n1️⃣ این ویدئو هیچ پیش نیازی نداره\n\n✉️ تماشا در تلگرام \n\n📹 تماشا در یوتوب\n\n💰 دونیت"
    },
    {
      "post_id": "2785"
    },
    {
      "datetime": "2026-04-21T10:59:42+00:00",
      "time_text": "10:59",
      "link": "https://t.me/MatinSenPaii/2784",
      "views": "31.7K"
    },
    {
      "text": "مشت محکمی بر دهان شرکت‌های رانتی که دسترسی به یوتوب رو اشتراکی کردن:\n\nhttps://github.com/masterking32/MasterHttpRelayVPN/blob/python_testing/README_FA.md\nو\nhttps://github.com/patterniha/MITM-DomainFronting\nرو تست کنید. توضیحات کامل توی Readme هست"
    },
    {
      "post_id": "2784"
    },
    {
      "datetime": "2026-04-20T21:56:41+00:00",
      "time_text": "21:56",
      "link": "https://t.me/MatinSenPaii/2783",
      "views": "31.1K"
    },
    {
      "text": "بیننده خودش عاقله. اگر عاقل نباشه همون بهتر که بره دنبال سایت رانتی"
    },
    {
      "text": "متین الان لینکدونی باید بابت این حرکتت بهت یه چی بده😂😂"
    },
    {
      "post_id": "2783"
    },
    {
      "datetime": "2026-04-20T21:52:20+00:00",
      "time_text": "21:52",
      "link": "https://t.me/MatinSenPaii/2781",
      "views": "30.9K"
    },
    {
      "text": "نکته خنده‌دار: چند نفر از دوستان رفتن خریدن همونم درست کار نمیکنه گویا🤣🤣"
    },
    {
      "photos": [
        "bale:46627310:-4672396415646556415:1:65b5e3e3fd6f689bc1ad95653c1893c18211e6c76420e4b7"
      ]
    },
    {
      "photos": [
        "bale:46627310:7741524315807162114:1:65b5e3e3fd6f689bc1ad95653c1893c18211e6c76420e4b7"
      ]
    },
    {
      "text": "دسترسی به یوتوب با پول اشتراک&#33;  گویا با وارد شدن به سایت «لینکدونی» (از زیرمجموعه‌های افزونه دستیار) میتونید با وارد کردن شماره تلفنتون و پرداخت مبلغ ناقابل 130 هزار تومان به یوتوب دسترسی داشته باشید و حتی از یوتوب دانلود کنید&#33;"
    },
    {
      "post_id": "2781"
    }
  ],
  "fetch_metadata": {
    "last_update": "2026-04-21T22:10:20.812981",
    "new_count": 0
  }
}