{
  "success": true,
  "channel": "ne_wg",
  "channel_title": "خبرفوری ࡆ اخبارفوری ࡆ جنگ فوری امریکا",
  "channel_username": "@ne_wg",
  "channel_avatar": "bale:46627310:4453395305945112323:1:65b5e3e3fd6f689ba80ee913c321ca448211e6c76420e4b7",
  "channel_verified": false,
  "channel_subscribers": "4.32M",
  "channel_photos": null,
  "channel_videos": null,
  "channel_files": null,
  "channel_links": null,
  "channel_description": "﷽\n\nبا ما فقط یک کانال خبری را دنبال کنید.\nمستقل ترین اخبار ایران\n\n تبلیغات:\n@Ads_setare1\n.\n\nارتباط و ارسال گزارشات:\n@khabarfori_support\n\n.",
  "total_posts": 73,
  "returned_posts": 73,
  "posts": [
    {
      "datetime": "2026-04-23T05:36:19+00:00",
      "time_text": "05:36",
      "link": "https://t.me/NE_WG/93802",
      "views": "6.91K"
    },
    {
      "text": "💢سناتور آمریکایی کریس مورفی: خسارات ناشی از جنگ ترامپ با ایران می‌تواند بدتر شود، زیرا امتناع او از پایان دادن به جنگ، تهران را در کنترل هرمز قرار می‌دهد و قیمت انرژی را به طرز فاجعه‌باری بالا نگه می‌دارد\n\n🔖 @News1Fori"
    },
    {
      "photos": [
        "bale:46627310:-7344048466453848320:1:65b5e3e3fd6f689b56b480ecd506ea238211e6c76420e4b7"
      ]
    },
    {
      "post_id": "93802"
    },
    {
      "datetime": "2026-04-23T03:26:04+00:00",
      "time_text": "03:26",
      "link": "https://t.me/NE_WG/93801",
      "views": "16.2K"
    },
    {
      "text": "💢نیویورک‌تایمز: از زمان آغاز جنگ آمریکا با ایران، ۳۰۸ کشتیِ مرتبط با ایران از تنگه هرمز عبور کرده‌اند\n\n🔖 @News1Fori"
    },
    {
      "photos": [
        "bale:46627310:-8320364747535671549:1:65b5e3e3fd6f689ba41dde7f0e377d728211e6c76420e4b7"
      ]
    },
    {
      "post_id": "93801"
    },
    {
      "datetime": "2026-04-23T01:31:20+00:00",
      "time_text": "01:31",
      "link": "https://t.me/NE_WG/93800",
      "views": "19.7K"
    },
    {
      "text": "🔴فاکس نیوز: ناوگروه «بوش» ۳ تا ۵ روز دیگر به خاورمیانه می‌رسد&#33;\n\n🔖 @News1Fori"
    },
    {
      "post_id": "93800"
    },
    {
      "datetime": "2026-04-23T00:48:26+00:00",
      "time_text": "00:48",
      "link": "https://t.me/NE_WG/93799",
      "views": "21.5K"
    },
    {
      "text": "🇺🇸🇮🇷 مرکز فرماندهی مرکزی ایالات متحده (CENTCOM) مروری بر محاصره جاری بنادر ایران منتشر کرد و اعلام کرد که نیروهای آمریکایی مسیر بیش از ۳۰ کشتی، که اکثر آن‌ها نفت‌کش هستند، را تغییر داده‌اند، در حالی که بیش از ۱۰,۰۰۰ سرباز، بیش از ۱۰۰ هواپیما و حداقل ۱۷ کشتی جنگی را مستقر کرده‌اند.\n\n🔖 @News1Fori"
    },
    {
      "photos": [
        "bale:46627310:-873306628788052224:1:65b5e3e3fd6f689bce0e638d017c06fa8211e6c76420e4b7"
      ]
    },
    {
      "post_id": "93799"
    },
    {
      "datetime": "2026-04-23T00:37:00+00:00",
      "time_text": "00:37",
      "link": "https://t.me/NE_WG/93798",
      "views": "21.5K"
    },
    {
      "text": "‼️نفت برنت به ۱۰۵ دلار رسید&#33;\n\n🔖 @News1Fori"
    },
    {
      "photos": [
        "bale:46627310:4950817293437181698:1:65b5e3e3fd6f689b7d9a472caf78f52c8211e6c76420e4b7"
      ]
    },
    {
      "post_id": "93798"
    },
    {
      "datetime": "2026-04-23T00:32:34+00:00",
      "time_text": "00:32",
      "link": "https://t.me/NE_WG/93797",
      "views": "21.1K"
    },
    {
      "text": "🔴رسانه‌های داخلی: صدای انفجار در پردیس مربوط به خنثی سازی بمب هایی که در زمان جنگ عمل نکردند هستش و هیچ حمله‌ای صورت نگرفته&#33;\n\n🔖 @News1Fori"
    },
    {
      "post_id": "93797"
    },
    {
      "datetime": "2026-04-23T00:04:37+00:00",
      "time_text": "00:04",
      "link": "https://t.me/NE_WG/93796",
      "views": "22.7K"
    },
    {
      "text": "💢پس از شناسایی اشیاء ناشناس که از پایگاه‌های آمریکایی در کویت پرتاب می‌شدند، اکنون پدافند هوایی در آسمان تهران، پایتخت، فعال شده است.\n\n🔖 @News1Fori"
    },
    {
      "videos": [
        "bale:46627310:4456686259064741632:1:65b5e3e3fd6f689be4b1e0014ffeb87178bd75520bbfc49a"
      ]
    },
    {
      "videos": [
        "bale:46627310:4456686259064741632:1:65b5e3e3fd6f689be4b1e0014ffeb87178bd75520bbfc49a"
      ]
    },
    {
      "post_id": "93796"
    },
    {
      "datetime": "2026-04-22T23:33:01+00:00",
      "time_text": "23:33",
      "link": "https://t.me/NE_WG/93795",
      "views": "22.8K"
    },
    {
      "text": "✅ برنی سندرز، سناتور آمریکایی در واکنش به خبر کمک اقتصادی آمریکا به امارات: به من بگویید افراطی، اما فکر نمی‌کنم باید میلیون‌ها آمریکایی را از پوشش بهداشت و درمان محروم کنیم در حالی که یک دیکتاتور بی‌رحم را که دارایی خانواده‌اش ۳۰۰ میلیارد دلار است، نجات دهیم\n\n🔖 @News1Fori"
    },
    {
      "photos": [
        "bale:46627310:5623420528824491779:1:65b5e3e3fd6f689b1c11a4434546a2778211e6c76420e4b7"
      ]
    },
    {
      "post_id": "93795"
    },
    {
      "datetime": "2026-04-22T22:59:42+00:00",
      "time_text": "22:59",
      "link": "https://t.me/NE_WG/93794",
      "views": "23.2K"
    },
    {
      "text": "🌐 اینترنت بدون قطعی از اول جنگ تا الان&#33; \n\n⚡ سرعت و کیفیت بالا\n✅ بدون قطعی و با اتصال پایدار در تمام روز\n✅ مناسب برای استفاده از اینستاگرام، تلگرام، ترید، و وب‌گردی با سرعت عالی\n\n💥 پک ویژه: ۵ گیگ اینترنت فقط ۱۸۰۰ میلیون تومان(گیگی ۳۵۰ هزار تومان) 💥\n\n📩 آیدی جهت خرید:\n@Royana_support\n📌 کانال جدید ما:\n@RoyanaNet"
    },
    {
      "post_id": "93794"
    },
    {
      "datetime": "2026-04-22T22:40:10+00:00",
      "time_text": "22:40",
      "link": "https://t.me/NE_WG/93793",
      "views": "23.5K"
    },
    {
      "text": "🇺🇸🇮🇷❌طرح کاهش اختیارات جنگی ترامپ بازهم رأی نیاورد\n\n🔹 مجلس سنای آمریکا با اکثریت جمهوری‌خواه برای بار پنجم به طرح دموکرات‌ها برای کاهش اختیارات جنگی دونالد ترامپ و پایان جنگ ایران رأی منفی داد.\n\n🔖 @News1Fori"
    },
    {
      "photos": [
        "bale:46627310:4210720446421409537:1:65b5e3e3fd6f689b4198ef74f0ad81478211e6c76420e4b7"
      ]
    },
    {
      "post_id": "93793"
    },
    {
      "datetime": "2026-04-22T22:24:52+00:00",
      "time_text": "22:24",
      "link": "https://t.me/NE_WG/93792",
      "views": "23.4K"
    },
    {
      "text": "♦️ پیشنهاد فرستاده ارشد ترامپ به رئیس فیفا: ایران را از جام جهانی کنار بگذارید و ایتالیا را بیاورید\n\n🔹 یکی از فرستادگان ارشد دونالد ترامپ به رئیس فیفا، جیانی اینفانتینو، و رئیس‌جمهور آمریکا، به عنوان رهبر کشور میزبان مشترک مسابقات، پیشنهاد کنار گذاشتن تیم ملی ایران را مطرح و جایگزینی آن با ایتالیا شد و استدلال کرد چهار قهرمانی ایتالیا در تاریخ این مسابقات، توجیه‌کننده اعطای آن سهمیه به این کشور است.\n\n🔖 @News1Fori"
    },
    {
      "photos": [
        "bale:46627310:-2239619238191030526:1:65b5e3e3fd6f689b4198ef74f0ad81478211e6c76420e4b7"
      ]
    },
    {
      "post_id": "93792"
    },
    {
      "datetime": "2026-04-22T22:07:02+00:00",
      "time_text": "22:07",
      "link": "https://t.me/NE_WG/93790",
      "views": "22.7K"
    },
    {
      "text": "🇺🇸💢پنتاگون: جان سی. فیلان، وزیر نیروی دریایی آمریکا، از سمت خود کناره‌گیری کرد&#33;\n\n🔖 @News1Fori"
    },
    {
      "photos": [
        "bale:46627310:-8582852664857190656:1:65b5e3e3fd6f689b74bef5696987d9a28211e6c76420e4b7"
      ]
    },
    {
      "photos": [
        "bale:46627310:-6415582417301790974:1:65b5e3e3fd6f689b74bef5696987d9a28211e6c76420e4b7"
      ]
    },
    {
      "post_id": "93790"
    },
    {
      "datetime": "2026-04-22T21:57:17+00:00",
      "time_text": "21:57",
      "link": "https://t.me/NE_WG/93789",
      "views": "22.8K"
    },
    {
      "text": "🇮🇷🇺🇸🚫رویترز به نقل از منابع کشتیرانی گزارش داد: ارتش آمریکا سه نفتکش ایرانی را در آب‌های آسیا توقیف کرد\n\n🔖 @News1Fori"
    },
    {
      "post_id": "93789"
    },
    {
      "datetime": "2026-04-22T21:49:16+00:00",
      "time_text": "21:49",
      "link": "https://t.me/NE_WG/93788",
      "views": "23.4K"
    },
    {
      "text": "🇮🇱🇮🇷💢دو تکنسین نیروی هوایی اسرائیل به جرم جاسوسی متهم شده‌اند که به گفته مقامات، اطلاعات فنی و عکس‌های مربوط به جنگنده‌های اف-۱۵ را به ایران منتقل کرده‌اند.\n\n💢متهمان که در تل نوف مستقر بودند، چندین هفته بازداشت بودند و اکنون برای پیگرد قانونی آماده شده‌اند.\n\n🔖 @News1Fori"
    },
    {
      "photos": [
        "bale:46627310:-827253615593840896:1:65b5e3e3fd6f689bef1923ee09de60198211e6c76420e4b7"
      ]
    },
    {
      "post_id": "93788"
    },
    {
      "datetime": "2026-04-22T21:39:55+00:00",
      "time_text": "21:39",
      "link": "https://t.me/NE_WG/93787",
      "views": "22.8K"
    },
    {
      "text": "🇺🇸🇮🇷♦️سی‌ان‌ان: ترامپ تاکنون پنج بار برای ایران ضرب‌الاجل تعیین کرده است\n\n🔹 این ضرب‌الاجل هر بار تمدید شده است، با وجود اینکه ایران کاری را که ترامپ خواسته بود، انجام نداده است.\n\n🔖 @News1Fori"
    },
    {
      "post_id": "93787"
    },
    {
      "datetime": "2026-04-22T21:22:37+00:00",
      "time_text": "21:22",
      "link": "https://t.me/NE_WG/93786",
      "views": "23.8K"
    },
    {
      "text": "💢💢اولین تصاویر از توقیف کشتی‌های کانتینربر در تنگه هرمز&nbsp;توسط سپاه\n\n🔖 @News1Fori"
    },
    {
      "videos": [
        "bale:46627310:-3754665075853549821:1:65b5e3e3fd6f689bf67d30e566cb19fe78bd75520bbfc49a"
      ]
    },
    {
      "post_id": "93786"
    },
    {
      "datetime": "2026-04-22T21:11:14+00:00",
      "time_text": "21:11",
      "link": "https://t.me/NE_WG/93785",
      "views": "24K"
    },
    {
      "text": "🇺🇸ترامپ به فاکس نیوز: این ادعا که من می‌خواهم به دلیل انتخابات میان‌دوره‌ای به جنگ ایران پایان دهم، صحت ندارد، اصلا بخاطر انتخابات نیست&#33;\n\n🔖 @News1Fori"
    },
    {
      "text": "🇺🇸🇮🇷💢ترامپ به فاکس نیوز:   💢عراقچی مرد باهوشی است و من انتظار دارم که او در از سرگیری مذاکرات با ایران حضور داشته باشد.  💢ما به دنبال یک توافق خوب برای مردم آمریکا و جهان هستیم&#33;  💢هیچ فشار زمانی در مورد آتش‌بس یا توافق بر سر تاریخ جدید برای مذاکره با ایران…"
    },
    {
      "post_id": "93785"
    },
    {
      "datetime": "2026-04-22T21:04:35+00:00",
      "time_text": "21:04",
      "link": "https://t.me/NE_WG/93784",
      "views": "24.2K"
    },
    {
      "text": "🇺🇸🇮🇷💢ترامپ به فاکس نیوز: \n\n💢عراقچی مرد باهوشی است و من انتظار دارم که او در از سرگیری مذاکرات با ایران حضور داشته باشد.\n\n💢ما به دنبال یک توافق خوب برای مردم آمریکا و جهان هستیم&#33;\n\n💢هیچ فشار زمانی در مورد آتش‌بس یا توافق بر سر تاریخ جدید برای مذاکره با ایران وجود ندارد\n\n🔖 @News1Fori"
    },
    {
      "text": "💢ترامپ: ما به محاصره دریایی ایران ادامه می‌دهیم، هیچ زمان‌بندی مشخصی وجود ندارد&#33;  🔖 @News1Fori",
      "photos": [
        "bale:46627310:6847108100328267522:1:65b5e3e3fd6f689becadb13283d6e3cc8211e6c76420e4b7"
      ]
    },
    {
      "post_id": "93784"
    },
    {
      "datetime": "2026-04-22T20:58:25+00:00",
      "time_text": "20:58",
      "link": "https://t.me/NE_WG/93783",
      "views": "22.8K"
    },
    {
      "text": "💢ترامپ: ما به محاصره دریایی ایران ادامه می‌دهیم، هیچ زمان‌بندی مشخصی وجود ندارد&#33;\n\n🔖 @News1Fori"
    },
    {
      "photos": [
        "bale:46627310:-1820938671356502272:1:65b5e3e3fd6f689becadb13283d6e3cc8211e6c76420e4b7"
      ]
    },
    {
      "post_id": "93783"
    }
  ],
  "fetch_metadata": {
    "last_update": "2026-04-23T09:45:11.867949",
    "new_count": 0
  }
}